pratyush_102203958.py
topsis_102203958-1.0.8.dist-info/LICENSE
topsis_102203958-1.0.8.dist-info/METADATA
topsis_102203958-1.0.8.dist-info/WHEEL
topsis_102203958-1.0.8.dist-info/entry_points.txt
topsis_102203958-1.0.8.dist-info/top_level.txt
topsis_102203958-1.0.8.dist-info/RECORD
